MANIFEST.in
README.txt
setup.cfg
setup.py
archetypes/__init__.py
archetypes.languagebugfix.egg-info/PKG-INFO
archetypes.languagebugfix.egg-info/SOURCES.txt
archetypes.languagebugfix.egg-info/dependency_links.txt
archetypes.languagebugfix.egg-info/entry_points.txt
archetypes.languagebugfix.egg-info/namespace_packages.txt
archetypes.languagebugfix.egg-info/not-zip-safe
archetypes.languagebugfix.egg-info/requires.txt
archetypes.languagebugfix.egg-info/top_level.txt
archetypes/languagebugfix/README.txt
archetypes/languagebugfix/__init__.py
archetypes/languagebugfix/configure.zcml
archetypes/languagebugfix/patch.py
archetypes/languagebugfix/tests.py
archetypes/languagebugfix/version.txt
docs/HISTORY.txt
docs/INSTALL.txt
docs/LICENSE.GPL
docs/LICENSE.txt