Metadata-Version: 1.0
Name: archetypes.languagebugfix
Version: 1.0.2
Summary: This is a package to fix https://dev.plone.org/plone/ticket/8907
Home-page: http://www.simplesconsultoria.com.br/
Author: Simples Consultoria
Author-email: products@simplesconsultoria.com.br
License: GPL
Keywords: plone LinguaPlone i18n archetypes
Platform: UNKNOWN
Classifier: Framework :: Plone
Classifier: Programming Language :: Python
Classifier: Topic :: Software Development :: Libraries :: Python Modules
